asphalt/wamp/__init__.py
asphalt/wamp/client.py
asphalt/wamp/component.py
asphalt/wamp/context.py
asphalt/wamp/events.py
asphalt/wamp/extras_providers.py
asphalt/wamp/registry.py
asphalt/wamp/serializers.py
asphalt_wamp-2.2.2.dist-info/DESCRIPTION.rst
asphalt_wamp-2.2.2.dist-info/LICENSE.txt
asphalt_wamp-2.2.2.dist-info/METADATA
asphalt_wamp-2.2.2.dist-info/RECORD
asphalt_wamp-2.2.2.dist-info/WHEEL
asphalt_wamp-2.2.2.dist-info/entry_points.txt
asphalt_wamp-2.2.2.dist-info/metadata.json
asphalt_wamp-2.2.2.dist-info/top_level.txt
