Metadata-Version: 2.0
Name: asphalt-wamp
Version: 2.2.2
Summary: WAMP client component for the Asphalt framework
Home-page: https://github.com/asphalt-framework/asphalt-wamp
Author: Alex Grönholm
Author-email: alex.gronholm@nextday.fi
License: Apache License 2.0
Platform: UNKNOWN
Classifier: Development Status :: 5 - Production/Stable
Classifier: Environment :: Web Environment
Classifier: Intended Audience :: Developers
Classifier: License :: OSI Approved :: Apache Software License
Classifier: Topic :: Communications
Classifier: Programming Language :: Python
Classifier: Programming Language :: Python :: 3
Classifier: Programming Language :: Python :: 3.5
Classifier: Programming Language :: Python :: 3.6
Requires-Dist: asphalt (~=4.0)
Requires-Dist: asphalt-exceptions (~=1.0)
Requires-Dist: asphalt-serialization (~=4.0)
Requires-Dist: async-timeout (>=1.2)
Requires-Dist: autobahn (>=17.5.1)
Requires-Dist: typeguard (~=2.0)
Provides-Extra: doc
Requires-Dist: Sphinx (>=1.5); extra == 'doc'
Requires-Dist: sphinx-rtd-theme; extra == 'doc'
Requires-Dist: sphinx-autodoc-typehints (>=1.2.0); extra == 'doc'
Requires-Dist: sphinxcontrib-asyncio (>=0.2.0); extra == 'doc'
Provides-Extra: test
Requires-Dist: cbor2; extra == 'test'
Requires-Dist: msgpack-python; extra == 'test'
Requires-Dist: pytest; extra == 'test'
Requires-Dist: pytest-cov; extra == 'test'
Requires-Dist: pytest-asyncio (>=0.5.0); extra == 'test'
